setup.py
iress/__init__.py
iress/ado.py
iress/client.py
iress/typelibhelper.py
pyress.egg-info/PKG-INFO
pyress.egg-info/SOURCES.txt
pyress.egg-info/dependency_links.txt
pyress.egg-info/top_level.txt