Metadata-Version: 1.0
Name: pyress
Version: 0.2.0
Summary: Pythonic wrapper around the IRESS COM Interface.
Home-page: https://github.com/brotchie/pyress
Author: James Brotchie
Author-email: brotchie@gmail.com
License: Apache 2.0
Platform: win32
Classifier: Development Status :: 4 - Beta
Classifier: License :: OSI Approved :: Apache Software License
Classifier: Intended Audience :: Developers
Classifier: Programming Language :: Python
Classifier: Operating System :: Microsoft :: Windows
Classifier: Topic :: Office/Business :: Financial
Classifier: Environment :: Win32 (MS Windows)
